locking_activations/__init__.py
locking_activations/activations/__init__.py
locking_activations/experiments/__init__.py
locking_activations/saes/__init__.py
locking_activations-0.1.0.dist-info/LICENSE
locking_activations-0.1.0.dist-info/METADATA
locking_activations-0.1.0.dist-info/WHEEL
locking_activations-0.1.0.dist-info/top_level.txt
locking_activations-0.1.0.dist-info/RECORD
